add/__init__.py
add/aws.py
add/config/__init__.py
add/config/aws.py
add/config/general.py
add/config/log.py
add/resources/README.md
add/resources/README.rst
add/resources/requirements.txt
add/resources/scripts/add_update
add/resources/scripts/awsdd
awsdd-0.2.3.data/scripts/add_update
awsdd-0.2.3.data/scripts/awsdd
awsdd-0.2.3.dist-info/DESCRIPTION.rst
awsdd-0.2.3.dist-info/METADATA
awsdd-0.2.3.dist-info/metadata.json
awsdd-0.2.3.dist-info/RECORD
awsdd-0.2.3.dist-info/top_level.txt
awsdd-0.2.3.dist-info/WHEEL
