Metadata-Version: 2.0
Name: awsdd
Version: 0.2.3
Summary: An AWS (Route53)-based dynamic DNS client.
Home-page: https://github.com/dsoprea/AwsDynDns
Author: Dustin Oprea
Author-email: myselfasunder@gmail.com
License: GPL 2
Keywords: aws r53 route53 boto dyndns dynamic dns client
Platform: UNKNOWN
Requires-Dist: boto (==2.29.1)
Requires-Dist: requests (==2.3.0)
Requires-Dist: wsgiref (==0.1.2)
